LICENSE
MANIFEST.in
README.rst
setup.py
panopticon/__init__.py
panopticon/analysis.py
panopticon/clustering.py
panopticon/dna.py
panopticon/legacy.py
panopticon/preprocessing.py
panopticon/tcr.py
panopticon/utilities.py
panopticon/visualization.py
panopticon/widgets.py
panopticon/wme.py
panopticon/commands/__init__.py
panopticon/commands/bookem.py
panopticon/commands/multireference_dna_correspondence.py
panopticon/commands/rna_dna_correspondence.py
panopticon/commands/windowed_mean_expression_clustering.py
panopticon_single_cell.egg-info/PKG-INFO
panopticon_single_cell.egg-info/SOURCES.txt
panopticon_single_cell.egg-info/dependency_links.txt
panopticon_single_cell.egg-info/requires.txt
panopticon_single_cell.egg-info/top_level.txt
scripts/panopticon