Metadata-Version: 1.0
Name: panopticon-single-cell
Version: 0.3
Summary: for general analysis of single-cell RNA data
Home-page: UNKNOWN
Author: Samuel C. Markson
Author-email: smarkson@alum.mit.edu
License: BSD
Platform: UNKNOWN
